Metadata-Version: 1.0
Name: gausbinom-distributions-nraichur
Version: 0.1
Summary: Gaussian-Binomian distributions
Home-page: UNKNOWN
Author: Nisha
Author-email: nishalraichur@gmail.com
License: UNKNOWN
Platform: UNKNOWN
